autograder/__init__.py
autograder/__main__.py
autograder/assignment.py
autograder/code.py
autograder/error.py
autograder/fileop.py
autograder/filespec.py
autograder/question.py
autograder/style.py
autograder/submission.py
autograder/api/__init__.py
autograder/api/common.py
autograder/api/config.py
autograder/api/constants.py
autograder/api/courses/__init__.py
autograder/api/courses/admin/__init__.py
autograder/api/courses/admin/email.py
autograder/api/courses/admin/update.py
autograder/api/courses/assignments/__init__.py
autograder/api/courses/assignments/report.py
autograder/api/courses/assignments/submissions/__init__.py
autograder/api/courses/assignments/submissions/remove.py
autograder/api/courses/assignments/submissions/submit.py
autograder/api/courses/assignments/submissions/analysis/__init__.py
autograder/api/courses/assignments/submissions/analysis/individual.py
autograder/api/courses/assignments/submissions/analysis/pairwise.py
autograder/api/courses/assignments/submissions/fetch/__init__.py
autograder/api/courses/assignments/submissions/fetch/course/__init__.py
autograder/api/courses/assignments/submissions/fetch/course/attempts.py
autograder/api/courses/assignments/submissions/fetch/course/scores.py
autograder/api/courses/assignments/submissions/fetch/user/__init__.py
autograder/api/courses/assignments/submissions/fetch/user/attempt.py
autograder/api/courses/assignments/submissions/fetch/user/attempts.py
autograder/api/courses/assignments/submissions/fetch/user/history.py
autograder/api/courses/assignments/submissions/fetch/user/peek.py
autograder/api/courses/assignments/submissions/proxy/__init__.py
autograder/api/courses/assignments/submissions/proxy/regrade.py
autograder/api/courses/assignments/submissions/proxy/resubmit.py
autograder/api/courses/assignments/submissions/proxy/submit.py
autograder/api/courses/lms/__init__.py
autograder/api/courses/lms/scores/__init__.py
autograder/api/courses/lms/scores/upload.py
autograder_py-0.6.15.dist-info/licenses/LICENSE
autograder_py-0.6.15.dist-info/METADATA
autograder_py-0.6.15.dist-info/WHEEL
autograder_py-0.6.15.dist-info/top_level.txt
autograder_py-0.6.15.dist-info/RECORD
