Metadata-Version: 2.4
Name: autograder-py
Version: 0.6.15
Summary: The Python interface for the autograding server.
Author-email: Eriq Augustine <eriq@edulinq.org>
License: MIT License
Project-URL: Homepage, https://github.com/edulinq/autograder-py
Project-URL: Repository, https://github.com/edulinq/autograder-py
Keywords: education,grading
Classifier: Intended Audience :: Education
Classifier: License :: OSI Approved :: MIT License
Classifier: Programming Language :: Python :: 3.8
Requires-Python: >=3.8
License-File: LICENSE
Requires-Dist: argon2-cffi>=23.1.0
Requires-Dist: flake8>=6.0.0
Requires-Dist: GitPython>=3.1.31
Requires-Dist: platformdirs>=3.10.0
Requires-Dist: requests>=2.31.0
Provides-Extra: dev
Requires-Dist: build; extra == "dev"
Requires-Dist: packaging>=21.3; extra == "dev"
Requires-Dist: requests-toolbelt; extra == "dev"
Requires-Dist: twine; extra == "dev"
Requires-Dist: vermin; extra == "dev"
Dynamic: license-file
